[
  {
    "dateTime": "29/07/2025, 10:00 a. m.",
    "local": {
      "nombre": "Kairat",
      "logo": "https://cdn.sportmonks.com/images/soccer/teams/4/3108.png",
      "golesLocal": "3"
    },
    "visitante": {
      "nombre": "KuPS",
      "logo": "https://cdn.sportmonks.com/images/soccer/teams/3/4323.png",
      "golesVisitante": "0"
    },
    "estado": "FT",
    "destacado": {
      "pr": "1X",
      "odd": "1.08"
    },
    "cuotas": {
      "1": "1.38",
      "2": "7.00",
      "12": "1.16",
      "X": "4.75",
      "1X": "1.08",
      "X2": "3.00",
      "GG": "1.83",
      "NG": "1.83",
      "O15": "1.16",
      "U15": "4.50",
      "O25": "1.61",
      "U25": "2.25",
      "O35": "2.50",
      "U35": "1.50"
    },
    "resultados": {
      "1": true,
      "2": false,
      "12": true,
      "X": false,
      "1X": true,
      "X2": false,
      "GG": false,
      "NG": true,
      "O15": true,
      "U15": false,
      "O25": true,
      "U25": false,
      "O35": false,
      "U35": true
    },
    "probabilidades": {
      "1": 31,
      "2": 43,
      "12": 74,
      "X": 26,
      "1X": 57,
      "X2": 69,
      "GG": 55,
      "NG": 45,
      "O15": 76,
      "U15": 24,
      "O25": 51,
      "U25": 49,
      "O35": 30,
      "U35": 70
    }
  },
  {
    "dateTime": "29/07/2025, 10:30 a. m.",
    "local": {
      "nombre": "SJK Akatemia II",
      "logo": "https://cdn.sportmonks.com/images/soccer/team_placeholder.png",
      "golesLocal": "6"
    },
    "visitante": {
      "nombre": "VIFK",
      "logo": "https://cdn.sportmonks.com/images/soccer/teams/2/9058.png",
      "golesVisitante": "0"
    },
    "estado": "FT",
    "destacado": {
      "pr": "O25",
      "odd": "1.16"
    },
    "cuotas": {
      "1": "1.33",
      "2": "5.50",
      "12": "1.08",
      "X": "6.00",
      "1X": "1.10",
      "X2": "2.87",
      "GG": "1.36",
      "NG": "3.00",
      "O15": "1.04",
      "U15": "9.00",
      "O25": "1.16",
      "U25": "4.50",
      "O35": "1.44",
      "U35": "2.62"
    },
    "resultados": {
      "1": true,
      "2": false,
      "12": true,
      "X": false,
      "1X": true,
      "X2": false,
      "GG": false,
      "NG": true,
      "O15": true,
      "U15": false,
      "O25": true,
      "U25": false,
      "O35": true,
      "U35": false
    },
    "probabilidades": {
      "1": 62,
      "2": 23,
      "12": 85,
      "X": 15,
      "1X": 77,
      "X2": 38,
      "GG": 80,
      "NG": 20,
      "O15": 95,
      "U15": 5,
      "O25": 87,
      "U25": 13,
      "O35": 72,
      "U35": 28
    }
  },
  {
    "dateTime": "29/07/2025, 11:00 a. m.",
    "local": {
      "nombre": "FC Iberia 1999",
      "logo": "https://cdn.sportmonks.com/images/soccer/teams/24/6392.png",
      "golesLocal": "2"
    },
    "visitante": {
      "nombre": "Levadia",
      "logo": "https://cdn.sportmonks.com/images/soccer/teams/16/4400.png",
      "golesVisitante": "2"
    },
    "estado": "AET",
    "destacado": {
      "pr": "12",
      "odd": "1.28"
    },
    "cuotas": {
      "1": "1.60",
      "2": "5.25",
      "12": "1.28",
      "X": "3.60",
      "1X": "1.14",
      "X2": "2.25",
      "GG": "2.00",
      "NG": "1.72",
      "O15": "1.33",
      "U15": "3.25",
      "O25": "2.05",
      "U25": "1.75",
      "O35": "3.75",
      "U35": "1.25"
    },
    "resultados": {
      "1": true,
      "2": false,
      "12": true,
      "X": false,
      "1X": true,
      "X2": false,
      "GG": true,
      "NG": false,
      "O15": true,
      "U15": false,
      "O25": true,
      "U25": false,
      "O35": false,
      "U35": true
    },
    "probabilidades": {
      "1": 36,
      "2": 42,
      "12": 78,
      "X": 22,
      "1X": 58,
      "X2": 64,
      "GG": 59,
      "NG": 41,
      "O15": 81,
      "U15": 19,
      "O25": 59,
      "U25": 41,
      "O35": 38,
      "U35": 62
    }
  },
  {
    "dateTime": "29/07/2025, 01:00 p. m.",
    "local": {
      "nombre": "Drita",
      "logo": "https://cdn.sportmonks.com/images/soccer/teams/6/148038.png",
      "golesLocal": "0"
    },
    "visitante": {
      "nombre": "FC København",
      "logo": "https://cdn.sportmonks.com/images/soccer/teams/21/85.png",
      "golesVisitante": "1"
    },
    "estado": "FT",
    "destacado": {
      "pr": "12",
      "odd": "1.22"
    },
    "cuotas": {
      "1": "5.75",
      "2": "1.48",
      "12": "1.22",
      "X": "4.20",
      "1X": "2.62",
      "X2": "1.12",
      "GG": "1.90",
      "NG": "1.80",
      "O15": "1.25",
      "U15": "3.75",
      "O25": "1.80",
      "U25": "2.00",
      "O35": "2.75",
      "U35": "1.40"
    },
    "resultados": {
      "1": false,
      "2": true,
      "12": true,
      "X": false,
      "1X": false,
      "X2": true,
      "GG": false,
      "NG": true,
      "O15": false,
      "U15": true,
      "O25": false,
      "U25": true,
      "O35": false,
      "U35": true
    },
    "probabilidades": {
      "1": 22,
      "2": 54,
      "12": 76,
      "X": 24,
      "1X": 46,
      "X2": 78,
      "GG": 52,
      "NG": 48,
      "O15": 75,
      "U15": 25,
      "O25": 52,
      "U25": 48,
      "O35": 30,
      "U35": 70
    }
  },
  {
    "dateTime": "29/07/2025, 01:00 p. m.",
    "local": {
      "nombre": "Differdange 03",
      "logo": "https://cdn.sportmonks.com/images/soccer/teams/30/3998.png",
      "golesLocal": "1"
    },
    "visitante": {
      "nombre": "The New Saints",
      "logo": "https://cdn.sportmonks.com/images/soccer/teams/3/579.png",
      "golesVisitante": "0"
    },
    "estado": "FT",
    "destacado": {
      "pr": "12",
      "odd": "1.22"
    },
    "cuotas": {
      "1": "1.83",
      "2": "3.50",
      "12": "1.22",
      "X": "3.70",
      "1X": "1.22",
      "X2": "1.80",
      "GG": "1.66",
      "NG": "2.10",
      "O15": "1.22",
      "U15": "4.00",
      "O25": "1.70",
      "U25": "2.10",
      "O35": "2.75",
      "U35": "1.40"
    },
    "resultados": {
      "1": true,
      "2": false,
      "12": true,
      "X": false,
      "1X": true,
      "X2": false,
      "GG": false,
      "NG": true,
      "O15": false,
      "U15": true,
      "O25": false,
      "U25": true,
      "O35": false,
      "U35": true
    },
    "probabilidades": {
      "1": 37,
      "2": 38,
      "12": 75,
      "X": 25,
      "1X": 62,
      "X2": 63,
      "GG": 53,
      "NG": 47,
      "O15": 74,
      "U15": 26,
      "O25": 53,
      "U25": 47,
      "O35": 28,
      "U35": 72
    }
  },
  {
    "dateTime": "29/07/2025, 01:30 p. m.",
    "local": {
      "nombre": "Barnet",
      "logo": "https://cdn.sportmonks.com/images/soccer/teams/30/318.png",
      "golesLocal": "2"
    },
    "visitante": {
      "nombre": "Newport County",
      "logo": "https://cdn.sportmonks.com/images/soccer/teams/8/72.png",
      "golesVisitante": "2"
    },
    "estado": "FT_PEN",
    "destacado": {
      "pr": "O15",
      "odd": "1.22"
    },
    "cuotas": {
      "1": "1.70",
      "2": "4.75",
      "12": "1.25",
      "X": "3.90",
      "1X": "1.18",
      "X2": "2.10",
      "GG": "1.75",
      "NG": "2.00",
      "O15": "1.22",
      "U15": "4.00",
      "O25": "1.75",
      "U25": "2.05",
      "O35": "2.75",
      "U35": "1.40"
    },
    "resultados": {
      "1": null,
      "2": null,
      "12": null,
      "X": null,
      "1X": null,
      "X2": null,
      "GG": null,
      "NG": null,
      "O15": null,
      "U15": null,
      "O25": null,
      "U25": null,
      "O35": null,
      "U35": null
    },
    "probabilidades": {
      "1": 53,
      "2": 26,
      "12": 79,
      "X": 21,
      "1X": 74,
      "X2": 47,
      "GG": 54,
      "NG": 46,
      "O15": 82,
      "U15": 18,
      "O25": 54,
      "U25": 46,
      "O35": 41,
      "U35": 59
    }
  },
  {
    "dateTime": "29/07/2025, 02:00 p. m.",
    "local": {
      "nombre": "Crvena Zvezda",
      "logo": "https://cdn.sportmonks.com/images/soccer/teams/17/2673.png",
      "golesLocal": "5"
    },
    "visitante": {
      "nombre": "Lincoln Red Imps",
      "logo": "https://cdn.sportmonks.com/images//soccer/teams/20/10068.png",
      "golesVisitante": "1"
    },
    "estado": "FT",
    "destacado": {
      "pr": "1",
      "odd": "1.05"
    },
    "cuotas": {
      "1": "1.05",
      "2": "21.00",
      "12": "1.01",
      "X": "15.00",
      "1X": "1.00",
      "X2": "8.50",
      "GG": "2.10",
      "NG": "1.66",
      "O15": "1.04",
      "U15": "9.00",
      "O25": "1.16",
      "U25": "4.50",
      "O35": "1.44",
      "U35": "2.62"
    },
    "resultados": {
      "1": true,
      "2": false,
      "12": true,
      "X": false,
      "1X": true,
      "X2": false,
      "GG": true,
      "NG": false,
      "O15": true,
      "U15": false,
      "O25": true,
      "U25": false,
      "O35": true,
      "U35": false
    },
    "probabilidades": {
      "1": 66,
      "2": 15,
      "12": 81,
      "X": 19,
      "1X": 85,
      "X2": 34,
      "GG": 53,
      "NG": 47,
      "O15": 83,
      "U15": 17,
      "O25": 65,
      "U25": 36,
      "O35": 46,
      "U35": 54
    }
  },
  {
    "dateTime": "29/07/2025, 02:00 p. m.",
    "local": {
      "nombre": "Zrinjski",
      "logo": "https://cdn.sportmonks.com/images/soccer/teams/5/6213.png",
      "golesLocal": "2"
    },
    "visitante": {
      "nombre": "Slovan Bratislava",
      "logo": "https://cdn.sportmonks.com/images/soccer/teams/17/2417.png",
      "golesVisitante": "2"
    },
    "estado": "FT",
    "destacado": {
      "pr": "O15",
      "odd": "1.28"
    },
    "cuotas": {
      "1": "2.55",
      "2": "2.62",
      "12": "1.36",
      "X": "3.20",
      "1X": "1.44",
      "X2": "1.50",
      "GG": "1.80",
      "NG": "1.90",
      "O15": "1.28",
      "U15": "3.50",
      "O25": "2.00",
      "U25": "1.80",
      "O35": "3.40",
      "U35": "1.30"
    },
    "resultados": {
      "1": false,
      "2": false,
      "12": false,
      "X": true,
      "1X": true,
      "X2": true,
      "GG": true,
      "NG": false,
      "O15": true,
      "U15": false,
      "O25": true,
      "U25": false,
      "O35": true,
      "U35": false
    },
    "probabilidades": {
      "1": 48,
      "2": 28,
      "12": 77,
      "X": 23,
      "1X": 72,
      "X2": 52,
      "GG": 58,
      "NG": 42,
      "O15": 81,
      "U15": 19,
      "O25": 59,
      "U25": 41,
      "O35": 37,
      "U35": 63
    }
  },
  {
    "dateTime": "29/07/2025, 02:15 p. m.",
    "local": {
      "nombre": "Leiknir Reykjavík",
      "logo": "https://cdn.sportmonks.com/images/soccer/teams/27/9499.png",
      "golesLocal": "0"
    },
    "visitante": {
      "nombre": "Keflavík",
      "logo": "https://cdn.sportmonks.com/images/soccer/teams/19/10419.png",
      "golesVisitante": "2"
    },
    "estado": "FT",
    "destacado": {
      "pr": "12",
      "odd": "1.16"
    },
    "cuotas": {
      "1": "4.20",
      "2": "1.57",
      "12": "1.16",
      "X": "4.10",
      "1X": "2.15",
      "X2": "1.16",
      "GG": "1.50",
      "NG": "2.45",
      "O15": "1.15",
      "U15": "5.00",
      "O25": "1.53",
      "U25": "2.37",
      "O35": "2.25",
      "U35": "1.60"
    },
    "resultados": {
      "1": false,
      "2": true,
      "12": true,
      "X": false,
      "1X": false,
      "X2": true,
      "GG": false,
      "NG": true,
      "O15": true,
      "U15": false,
      "O25": false,
      "U25": true,
      "O35": false,
      "U35": true
    },
    "probabilidades": {
      "1": 23,
      "2": 56,
      "12": 79,
      "X": 21,
      "1X": 44,
      "X2": 77,
      "GG": 65,
      "NG": 35,
      "O15": 86,
      "U15": 14,
      "O25": 65,
      "U25": 35,
      "O35": 46,
      "U35": 54
    }
  },
  {
    "dateTime": "29/07/2025, 02:15 p. m.",
    "local": {
      "nombre": "Njardvík",
      "logo": "https://cdn.sportmonks.com/images/soccer/teams/23/10423.png",
      "golesLocal": "3"
    },
    "visitante": {
      "nombre": "HK",
      "logo": "https://cdn.sportmonks.com/images/soccer/teams/18/178.png",
      "golesVisitante": "0"
    },
    "estado": "FT",
    "destacado": {
      "pr": "O15",
      "odd": "1.14"
    },
    "cuotas": {
      "1": "1.50",
      "2": "4.75",
      "12": "1.16",
      "X": "4.20",
      "1X": "1.12",
      "X2": "2.30",
      "GG": "1.50",
      "NG": "2.50",
      "O15": "1.14",
      "U15": "5.50",
      "O25": "1.44",
      "U25": "2.62",
      "O35": "2.15",
      "U35": "1.65"
    },
    "resultados": {
      "1": true,
      "2": false,
      "12": true,
      "X": false,
      "1X": true,
      "X2": false,
      "GG": false,
      "NG": true,
      "O15": true,
      "U15": false,
      "O25": true,
      "U25": false,
      "O35": false,
      "U35": true
    },
    "probabilidades": {
      "1": 45,
      "2": 33,
      "12": 78,
      "X": 22,
      "1X": 67,
      "X2": 55,
      "GG": 63,
      "NG": 37,
      "O15": 85,
      "U15": 15,
      "O25": 67,
      "U25": 33,
      "O35": 45,
      "U35": 55
    }
  },
  {
    "dateTime": "29/07/2025, 03:30 p. m.",
    "local": {
      "nombre": "22 de Julio",
      "logo": "https://cdn.sportmonks.com/images/soccer/team_placeholder.png",
      "golesLocal": "1"
    },
    "visitante": {
      "nombre": "Leones del Norte",
      "logo": "https://cdn.sportmonks.com/images/soccer/teams/0/262304.png",
      "golesVisitante": "0"
    },
    "estado": "FT",
    "destacado": {
      "pr": "U35",
      "odd": "1.16"
    },
    "cuotas": {
      "1": "3.60",
      "2": "2.05",
      "12": "1.30",
      "X": "3.00",
      "1X": "1.61",
      "X2": "1.22",
      "GG": "2.03",
      "NG": "1.74",
      "O15": "1.41",
      "U15": "2.74",
      "O25": "2.35",
      "U25": "1.57",
      "O35": "4.15",
      "U35": "1.16"
    },
    "resultados": {
      "1": true,
      "2": false,
      "12": true,
      "X": false,
      "1X": true,
      "X2": false,
      "GG": false,
      "NG": true,
      "O15": false,
      "U15": true,
      "O25": false,
      "U25": true,
      "O35": false,
      "U35": true
    },
    "probabilidades": {
      "1": 33,
      "2": 34,
      "12": 67,
      "X": 33,
      "1X": 66,
      "X2": 67,
      "GG": 40,
      "NG": 60,
      "O15": 59,
      "U15": 41,
      "O25": 33,
      "U25": 67,
      "O35": 15,
      "U35": 85
    }
  },
  {
    "dateTime": "29/07/2025, 04:30 p. m.",
    "local": {
      "nombre": "Sportivo Luqueño",
      "logo": "https://cdn.sportmonks.com/images/soccer/teams/14/5582.png",
      "golesLocal": "2"
    },
    "visitante": {
      "nombre": "Nacional Asunción",
      "logo": "https://cdn.sportmonks.com/images/soccer/teams/24/3480.png",
      "golesVisitante": "1"
    },
    "estado": "FT",
    "destacado": {
      "pr": "U35",
      "odd": "1.18"
    },
    "cuotas": {
      "1": "3.70",
      "2": "2.00",
      "12": "1.36",
      "X": "2.87",
      "1X": "1.66",
      "X2": "1.25",
      "GG": "2.10",
      "NG": "1.66",
      "O15": "1.44",
      "U15": "2.62",
      "O25": "2.40",
      "U25": "1.53",
      "O35": "4.50",
      "U35": "1.18"
    },
    "resultados": {
      "1": true,
      "2": false,
      "12": true,
      "X": false,
      "1X": true,
      "X2": false,
      "GG": true,
      "NG": false,
      "O15": true,
      "U15": false,
      "O25": true,
      "U25": false,
      "O35": false,
      "U35": true
    },
    "probabilidades": {
      "1": 29,
      "2": 40,
      "12": 69,
      "X": 31,
      "1X": 60,
      "X2": 71,
      "GG": 45,
      "NG": 55,
      "O15": 62,
      "U15": 38,
      "O25": 37,
      "U25": 63,
      "O35": 17,
      "U35": 83
    }
  },
  {
    "dateTime": "29/07/2025, 05:00 p. m.",
    "local": {
      "nombre": "Botafogo",
      "logo": "https://cdn.sportmonks.com/images/soccer/teams/16/2864.png",
      "golesLocal": "2"
    },
    "visitante": {
      "nombre": "Bragantino",
      "logo": "https://cdn.sportmonks.com/images/soccer/teams/0/7808.png",
      "golesVisitante": "0"
    },
    "estado": "FT",
    "destacado": {
      "pr": "U35",
      "odd": "1.22"
    },
    "cuotas": {
      "1": "1.55",
      "2": "6.50",
      "12": "1.25",
      "X": "3.75",
      "1X": "1.11",
      "X2": "2.37",
      "GG": "2.20",
      "NG": "1.61",
      "O15": "1.40",
      "U15": "2.75",
      "O25": "2.25",
      "U25": "1.61",
      "O35": "4.00",
      "U35": "1.22"
    },
    "resultados": {
      "1": true,
      "2": false,
      "12": true,
      "X": false,
      "1X": true,
      "X2": false,
      "GG": false,
      "NG": true,
      "O15": true,
      "U15": false,
      "O25": false,
      "U25": true,
      "O35": false,
      "U35": true
    },
    "probabilidades": {
      "1": 53,
      "2": 22,
      "12": 75,
      "X": 25,
      "1X": 78,
      "X2": 47,
      "GG": 50,
      "NG": 50,
      "O15": 72,
      "U15": 28,
      "O25": 48,
      "U25": 52,
      "O35": 25,
      "U35": 75
    }
  },
  {
    "dateTime": "29/07/2025, 06:00 p. m.",
    "local": {
      "nombre": "Atlético Nacional",
      "logo": "https://cdn.sportmonks.com/images/soccer/teams/5/6597.png",
      "golesLocal": "1"
    },
    "visitante": {
      "nombre": "Cúcuta Deportivo",
      "logo": "https://cdn.sportmonks.com/images/soccer/teams/21/14645.png",
      "golesVisitante": "0"
    },
    "estado": "FT",
    "destacado": {
      "pr": "12",
      "odd": "1.25"
    },
    "cuotas": {
      "1": "1.40",
      "2": "8.00",
      "12": "1.25",
      "X": "3.90",
      "1X": "1.08",
      "X2": "2.70",
      "GG": "2.25",
      "NG": "1.62",
      "O15": "1.33",
      "U15": "3.10",
      "O25": "2.05",
      "U25": "1.73",
      "O35": "3.60",
      "U35": "1.25"
    },
    "resultados": {
      "1": true,
      "2": false,
      "12": true,
      "X": false,
      "1X": true,
      "X2": false,
      "GG": false,
      "NG": true,
      "O15": false,
      "U15": true,
      "O25": false,
      "U25": true,
      "O35": false,
      "U35": true
    },
    "probabilidades": {
      "1": 64,
      "2": 14,
      "12": 78,
      "X": 22,
      "1X": 86,
      "X2": 36,
      "GG": 47,
      "NG": 53,
      "O15": 73,
      "U15": 27,
      "O25": 47,
      "U25": 53,
      "O35": 25,
      "U35": 75
    }
  },
  {
    "dateTime": "29/07/2025, 06:30 p. m.",
    "local": {
      "nombre": "Grêmio",
      "logo": "https://cdn.sportmonks.com/images/soccer/teams/13/2925.png",
      "golesLocal": "2"
    },
    "visitante": {
      "nombre": "Fortaleza",
      "logo": "https://cdn.sportmonks.com/images/soccer/teams/5/3621.png",
      "golesVisitante": "1"
    },
    "estado": "FT",
    "destacado": {
      "pr": "1X",
      "odd": "1.30"
    },
    "cuotas": {
      "1": "2.15",
      "2": "3.40",
      "12": "1.33",
      "X": "3.25",
      "1X": "1.30",
      "X2": "1.66",
      "GG": "1.95",
      "NG": "1.80",
      "O15": "1.40",
      "U15": "3.00",
      "O25": "2.20",
      "U25": "1.65",
      "O35": "4.00",
      "U35": "1.25"
    },
    "resultados": {
      "1": true,
      "2": false,
      "12": true,
      "X": false,
      "1X": true,
      "X2": false,
      "GG": true,
      "NG": false,
      "O15": true,
      "U15": false,
      "O25": true,
      "U25": false,
      "O35": false,
      "U35": true
    },
    "probabilidades": {
      "1": 53,
      "2": 21,
      "12": 73,
      "X": 27,
      "1X": 79,
      "X2": 47,
      "GG": 45,
      "NG": 55,
      "O15": 68,
      "U15": 32,
      "O25": 42,
      "U25": 58,
      "O35": 20,
      "U35": 80
    }
  }
      ]
